[
  {
    "id": 1,
    "category": "Websites",
    "title": "Nielsen",
    "image": "/images/home/nielsen-md.jpg",
    "description_key": "nielsen.description",
    "indepth_key": "nielsen.indepth",
    "bullets_key": "nielsen.bullets",
    "width": 300,
    "height": 300,
    "technologies": [
      "Gutenberg",
      "Chart.js",
      "Google API",
      "WordPress",
      "JavaScript",
      "PHP",
      "React",
      "HTML",
      "CSS",
      "Tailwind CSS",
      "Alpine.js",
      "Figma",
      "Git",
      "Webpack",
      "REST API",
      "Accessibility (WCAG)"
    ],
    "url": "https://www.nielsen.com/"
  },
  {
    "id": 2,
    "category": "Websites",
    "title": "Learn Athlean-X",
    "image": "/images/home/learn-athleanx.png",
    "description_key": "learnAthleanx.description",
    "indepth_key": "learnAthleanx.indepth",
    "bullets_key": "learnAthleanx.bullets",
    "width": 300,
    "height": 300,
    "technologies": [
      "WordPress",
      "JavaScript",
      "PHP",
      "HTML",
      "CSS",
      "jQuery",
      "SCSS",
      "MySQL",
      "CPanel",
      "Git",
      "NPM",
      "Adobe Photoshop",
      "Adobe Illustrator",
      "API Integrations",
      "Meta API",
      "Google API",
      "TortoiseSVN",
      "Webpack",
      "SEO Optimization"
    ],
    "url": "https://www.athleanx.com/"
  },
  {
    "id": 3,
    "category": "Websites",
    "title": "Athlean-X",
    "image": "/images/home/athleanx-md.jpg",
    "description_key": "athleanx.description",
    "indepth_key": "athleanx.indepth",
    "bullets_key": "athleanx.bullets",
    "width": 300,
    "height": 300,
    "technologies": [
      "Laravel",
      "WordPress",
      "JavaScript",
      "PHP",
      "HTML",
      "CSS",
      "jQuery",
      "MySQL",
      "CPanel",
      "Git",
      "Composer",
      "API Integrations",
      "Meta API",
      "Google API",
      "Blade Templates",
      "Redis (for caching)"
    ],
    "url": "https://www.athleanx.com/"
  },
  {
    "id": 4,
    "category": "Websites",
    "title": "Athlean-X Portal",
    "image": "/images/home/athlean-online-md.jpg",
    "description_key": "athleanxPortal.description",
    "indepth_key": "athleanxPortal.indepth",
    "bullets_key": "athleanxPortal.bullets",
    "width": 300,
    "height": 300,
    "technologies": [
      "Zend Framework",
      "JavaScript",
      "PHP",
      "HTML",
      "CSS",
      "jQuery",
      "MySQL",
      "CPanel",
      "Google API",
      "Meta API",
      "Adobe Photoshop",
      "Adobe Illustrator",
      "Progressive Web Apps (PWA)",
      "REST API",
      "SVN"
    ],
    "url": "https://www.portal.athleanx.com/"
  },
  {
    "id": 5,
    "category": "Websites",
    "title": "Antamba",
    "image": "/images/home/antamba-md.jpg",
    "description_key": "antamba.description",
    "indepth_key": "antamba.indepth",
    "bullets_key": "antamba.bullets",
    "width": 300,
    "height": 300,
    "technologies": [
      "WordPress",
      "WooCommerce",
      "JavaScript",
      "PHP",
      "HTML",
      "CSS",
      "jQuery",
      "MySQL",
      "CPanel",
      "Meta API",
      "Google Analytics",
      "SEO Optimization",
      "Elementor"
    ],
    "url": "https://www.antamba.com/"
  },
  {
    "id": 6,
    "category": "Websites",
    "title": "Island Painting",
    "image": "/images/home/island-painting-md.jpg",
    "description_key": "islandPainting.description",
    "indepth_key": "islandPainting.indepth",
    "bullets_key": "islandPainting.bullets",
    "width": 300,
    "height": 300,
    "technologies": [
      "WordPress",
      "JavaScript",
      "PHP",
      "HTML",
      "CSS",
      "jQuery",
      "MySQL",
      "CPanel",
      "Meta API",
      "Google Analytics",
      "SEO Optimization"
    ],
    "url": "https://www.islandpaintinginc.com/"
  },
  {
    "id": 7,
    "category": "Websites",
    "title": "Bikerevier",
    "image": "/images/home/bikerevier.png",
    "description_key": "bikerevier.description",
    "indepth_key": "bikerevier.indepth",
    "bullets_key": "bikerevier.bullets",
    "width": 300,
    "height": 300,
    "technologies": [
      "WordPress",
      "WooCommerce",
      "JavaScript",
      "PHP",
      "HTML",
      "CSS",
      "jQuery",
      "MySQL",
      "CPanel",
      "Elementor",
      "Google Analytics",
      "SEO Optimization"
    ],
    "url": "https://bikerevier.ch/"
  }
]
